vitabel/__init__.py
vitabel/timeseries.py
vitabel/typing.py
vitabel/vitals.py
vitabel/assets/circ-classification_model.joblib
vitabel/assets/circ-classification_scaler.joblib
vitabel/utils/__init__.py
vitabel/utils/constants.py
vitabel/utils/helpers.py
vitabel/utils/loading.py
vitabel/utils/stylesheet.py
vitabel-0.1.0.dist-info/METADATA
vitabel-0.1.0.dist-info/WHEEL
vitabel-0.1.0.dist-info/licenses/LICENSE
vitabel-0.1.0.dist-info/RECORD
