Metadata-Version: 2.4
Name: vitabel
Version: 0.1.0
Summary: A toolbox for plotting and interactively labeling vital data.
Project-URL: repository, https://github.com/UniGrazMath/vitabel
Project-URL: documentation, https://vitabel.readthedocs.io
Author-email: "Wolfgang J. Kern" <wolfgangjohannkern@gmail.com>, Benjamin Hackl <benjamin.hackl@uni-graz.at>, Simon Orlob <science@orlob.md>
License: MIT License
License-File: LICENSE
Requires-Python: >=3.10
Requires-Dist: ipykernel>=6.9
Requires-Dist: ipympl>=0.9.5
Requires-Dist: ipython>=8.23.0
Requires-Dist: ipywidgets>=8.1.5
Requires-Dist: joblib>=1.4.0
Requires-Dist: matplotlib>=3.9
Requires-Dist: numpy>=2.0.0
Requires-Dist: pandas>=2.2.3
Requires-Dist: pyedflib>=0.1.38
Requires-Dist: scikit-learn>=1.5.2
Requires-Dist: scipy>=1.14.1
Requires-Dist: typing-extensions>=4.12.2; python_full_version < '3.11'
Requires-Dist: vitaldb>=1.4.11
